[
    {
        "name": "Friday the 13th",
        "tmdbId": 4488,
        "mediaType": "movie",
        "backdropPath": "/16zzKM5vDxnYiqG6Tg6wOkOLSmj.jpg"
    },
    {
        "name": "Friday the 13th Part 2",
        "tmdbId": 9725,
        "mediaType": "movie",
        "backdropPath": "/80emEEa0svrT0YJDZLgLUu85ttp.jpg"
    },
    {
        "name": "Friday the 13th Part III",
        "tmdbId": 9728,
        "mediaType": "movie",
        "backdropPath": "/dtEkXmWPRwja6CtwPFcVpuMb7tW.jpg"
    },
    {
        "name": "Friday the 13th: The Final Chapter",
        "tmdbId": 9730,
        "mediaType": "movie",
        "backdropPath": "/2bbEE2aLu47unsPJwS57UZW0YF4.jpg"
    },
    {
        "name": "Friday the 13th: A New Beginning",
        "tmdbId": 9731,
        "mediaType": "movie",
        "backdropPath": "/pQy1GaR0TLwvb3Bpqk5teovzoDY.jpg"
    },
    {
        "name": "Friday the 13th Part VI: Jason Lives",
        "tmdbId": 10225,
        "mediaType": "movie",
        "backdropPath": "/93tvkTtV6tQQiYhxhij9tuODNOq.jpg"
    },
    {
        "name": "Friday the 13th Part VII: The New Blood",
        "tmdbId": 10281,
        "mediaType": "movie",
        "backdropPath": "/roHX6N0VkySKBlramHUw1zdMQHB.jpg"
    },
    {
        "name": "Friday the 13th Part VIII: Jason Takes Manhattan",
        "tmdbId": 10283,
        "mediaType": "movie",
        "backdropPath": "/6U5sEPgkf3nnQC51kUUKcKzNSyR.jpg"
    },
    {
        "name": "Jason Goes to Hell: The Final Friday",
        "tmdbId": 10285,
        "mediaType": "movie",
        "backdropPath": "/wqRyyOZcMaUxTnKsxDexPp4IAZ5.jpg"
    },
    {
        "name": "Jason X",
        "tmdbId": 11470,
        "mediaType": "movie",
        "backdropPath": "/fR5Hkf4OH6aLExl2qP2ucMV2Xdt.jpg"
    },
    {
        "name": "Freddy vs. Jason",
        "tmdbId": 6466,
        "mediaType": "movie",
        "backdropPath": "/hCAOQTMRop2fHjsl8n7yNwpkMJn.jpg"
    },
    {
        "name": "Friday the 13th",
        "tmdbId": 13207,
        "mediaType": "movie",
        "backdropPath": "/rpb9eBNpYjqSI3dLLniZ0GXcnlS.jpg"
    }
]