[
    {
        "name": "The Name of the Game",
        "tmdbId": 11978,
        "mediaType": "tv",
        "backdropPath": "/7TNIH7x3l3jSQfOZEW9F0kJrT7M.jpg"
    },
    {
        "name": "Amblin'",
        "tmdbId": 97105,
        "mediaType": "movie",
        "backdropPath": "/zbgBfigzYTbgFugbhIWMRWgQM4L.jpg"
    },
    {
        "name": "Marcus Welby, M.D.",
        "tmdbId": 3213,
        "mediaType": "tv",
        "backdropPath": "/9SZWGari27b3SNIKXPKGkXPZ91n.jpg"
    },
    {
        "name": "Night Gallery",
        "tmdbId": 391069,
        "mediaType": "movie",
        "backdropPath": "/ik66StCvdrPcptl1SioAIh2kOEc.jpg"
    },
    {
        "name": "Night Gallery",
        "tmdbId": 4318,
        "mediaType": "tv",
        "backdropPath": "/bC6p6I0PUqf1DMihOw2Y61gvzeb.jpg"
    },
    {
        "name": "The Psychiatrist",
        "tmdbId": 685,
        "mediaType": "tv",
        "backdropPath": ""
    },
    {
        "name": "Columbo",
        "tmdbId": 873,
        "mediaType": "tv",
        "backdropPath": "/2emkZBBiZG7pE7RBuIWtbKZ2a33.jpg"
    },
    {
        "name": "Owen Marshall: Counselor at Law",
        "tmdbId": 10168,
        "mediaType": "tv",
        "backdropPath": ""
    },
    {
        "name": "Duel",
        "tmdbId": 839,
        "mediaType": "movie",
        "backdropPath": "/AoGLKkPvBcZP27jwSA85fY8emvJ.jpg"
    },
    {
        "name": "Something Evil",
        "tmdbId": 85483,
        "mediaType": "movie",
        "backdropPath": "/2og6dqoazyVl30uofnQ62yTiJvj.jpg"
    },
    {
        "name": "Savage",
        "tmdbId": 110747,
        "mediaType": "movie",
        "backdropPath": "/yl73Eb3Hvu5zYAFGv0wN5agW6Mh.jpg"
    },
    {
        "name": "The Sugarland Express",
        "tmdbId": 5121,
        "mediaType": "movie",
        "backdropPath": "/cssKLoKClpgqaaGD2z3cjXgzPSM.jpg"
    },
    {
        "name": "Jaws",
        "tmdbId": 578,
        "mediaType": "movie",
        "backdropPath": "/i1yf91svRHX45l9BXL8rVFzLoPH.jpg"
    },
    {
        "name": "Close Encounters of the Third Kind",
        "tmdbId": 840,
        "mediaType": "movie",
        "backdropPath": "/yBCekmb7vK70xUhtsRQBcTu65sB.jpg"
    },
    {
        "name": "1941",
        "tmdbId": 11519,
        "mediaType": "movie",
        "backdropPath": "/wtJIV3BI3FbCJ2wKJCb9KngdEv2.jpg"
    },
    {
        "name": "Raiders of the Lost Ark",
        "tmdbId": 85,
        "mediaType": "movie",
        "backdropPath": "/zPACwR32amTNvzId9qyapCWXYDJ.jpg"
    },
    {
        "name": "E.T. the Extra-Terrestrial",
        "tmdbId": 601,
        "mediaType": "movie",
        "backdropPath": "/mXLVA0YL6tcXi6SJSuAh9ONXFj5.jpg"
    },
    {
        "name": "Twilight Zone: The Movie",
        "tmdbId": 15301,
        "mediaType": "movie",
        "backdropPath": "/6nRWWMNoA3uU6tgAny6GwvbYhQp.jpg"
    },
    {
        "name": "Indiana Jones and the Temple of Doom",
        "tmdbId": 87,
        "mediaType": "movie",
        "backdropPath": "/f133nWlU6yUkZqqwcCXCbTEJWHr.jpg"
    },
    {
        "name": "Amazing Stories",
        "tmdbId": 1026,
        "mediaType": "tv",
        "backdropPath": "/vDZ8fJhiMDVINf7mJcmKj6pYaYV.jpg"
    },
    {
        "name": "The Color Purple",
        "tmdbId": 873,
        "mediaType": "movie",
        "backdropPath": "/lh6MbyxwCribn3hdAo81xLdPGoV.jpg"
    },
    {
        "name": "Amazing Stories",
        "tmdbId": 576510,
        "mediaType": "movie",
        "backdropPath": "/cl2PJfdyV1PlmNvzsSEsajUCbHQ.jpg"
    },
    {
        "name": "Empire of the Sun",
        "tmdbId": 10110,
        "mediaType": "movie",
        "backdropPath": "/xt7boIC763DdceVQIGJdnmKlDVu.jpg"
    },
    {
        "name": "Indiana Jones and the Last Crusade",
        "tmdbId": 89,
        "mediaType": "movie",
        "backdropPath": "/12fvZHskx57kQfNEUXJ3v0flWYQ.jpg"
    },
    {
        "name": "Always",
        "tmdbId": 11352,
        "mediaType": "movie",
        "backdropPath": "/pIb1CLl08DxciZXJr7AK4qmkArA.jpg"
    },
    {
        "name": "Amazing Stories: The Movie II",
        "tmdbId": 1309288,
        "mediaType": "movie",
        "backdropPath": ""
    },
    {
        "name": "Hook",
        "tmdbId": 879,
        "mediaType": "movie",
        "backdropPath": "/39OxcFZjX4uc6vYzexUh5qXghxE.jpg"
    },
    {
        "name": "Jurassic Park",
        "tmdbId": 329,
        "mediaType": "movie",
        "backdropPath": "/alqZDg4DXBpNCVTzRPXe5zkkAXX.jpg"
    },
    {
        "name": "Schindler's List",
        "tmdbId": 424,
        "mediaType": "movie",
        "backdropPath": "/zb6fM1CX41D9rF9hdgclu0peUmy.jpg"
    },
    {
        "name": "The Lost World: Jurassic Park",
        "tmdbId": 330,
        "mediaType": "movie",
        "backdropPath": "/A4rYaPdzgocCjQ0n9LUSYUxyvpS.jpg"
    },
    {
        "name": "Amistad",
        "tmdbId": 11831,
        "mediaType": "movie",
        "backdropPath": "/6dTbovP5RdrNjroTpke0DQAvidN.jpg"
    },
    {
        "name": "Saving Private Ryan",
        "tmdbId": 857,
        "mediaType": "movie",
        "backdropPath": "/rW2xRFlJRbTnBJlQTSjQmjevIwb.jpg"
    },
    {
        "name": "The Unfinished Journey",
        "tmdbId": 793912,
        "mediaType": "movie",
        "backdropPath": "/dYEcUVuznENlk8bkAxUO9k00Q4s.jpg"
    },
    {
        "name": "A.I. Artificial Intelligence",
        "tmdbId": 644,
        "mediaType": "movie",
        "backdropPath": "/2tQ0Uhav10ay7jOX6QoqvbtGljB.jpg"
    },
    {
        "name": "Minority Report",
        "tmdbId": 180,
        "mediaType": "movie",
        "backdropPath": "/PrMb3oeEluauy0q9ZO5xL33A6C.jpg"
    },
    {
        "name": "Catch Me If You Can",
        "tmdbId": 640,
        "mediaType": "movie",
        "backdropPath": "/ggC3Brchf4RqPitEh7cROFoeAWn.jpg"
    },
    {
        "name": "The Terminal",
        "tmdbId": 594,
        "mediaType": "movie",
        "backdropPath": "/zywtNiaZ9r7azrcNdl2j0jOgrkw.jpg"
    },
    {
        "name": "War of the Worlds",
        "tmdbId": 74,
        "mediaType": "movie",
        "backdropPath": "/bInicBgSHfQiWLbnRT5jxw9Grvm.jpg"
    },
    {
        "name": "Munich",
        "tmdbId": 612,
        "mediaType": "movie",
        "backdropPath": "/titl6uMe5u974sLAA2Zy1kFi4sC.jpg"
    },
    {
        "name": "Indiana Jones and the Kingdom of the Crystal Skull",
        "tmdbId": 217,
        "mediaType": "movie",
        "backdropPath": "/p96949hcwUG2BwE6MgKmw0uYNCx.jpg"
    },
    {
        "name": "A Timeless Call",
        "tmdbId": 1198548,
        "mediaType": "movie",
        "backdropPath": ""
    },
    {
        "name": "The Adventures of Tintin",
        "tmdbId": 17578,
        "mediaType": "movie",
        "backdropPath": "/6mqgl2szMLRYj4lhlXOjju5Tpeo.jpg"
    },
    {
        "name": "War Horse",
        "tmdbId": 57212,
        "mediaType": "movie",
        "backdropPath": "/tcx15vswrQJCGET5lGxESQ4J5LG.jpg"
    },
    {
        "name": "Lincoln",
        "tmdbId": 72976,
        "mediaType": "movie",
        "backdropPath": "/hwOFrwHladQ8FktYn3aJNAt8KA1.jpg"
    },
    {
        "name": "Bridge of Spies",
        "tmdbId": 296098,
        "mediaType": "movie",
        "backdropPath": "/12M3SvYO4WMdlXCajWklz1zUAly.jpg"
    },
    {
        "name": "The BFG",
        "tmdbId": 267935,
        "mediaType": "movie",
        "backdropPath": "/tOTtJelsPKX0bvSdvDVL2ou3cGS.jpg"
    },
    {
        "name": "The Post",
        "tmdbId": 446354,
        "mediaType": "movie",
        "backdropPath": "/h5jqLrIv1tlszezv2UEWq9KBuoj.jpg"
    },
    {
        "name": "Ready Player One",
        "tmdbId": 333339,
        "mediaType": "movie",
        "backdropPath": "/5a7lMDn3nAj2ByO0X1fg6BhUphR.jpg"
    },
    {
        "name": "West Side Story",
        "tmdbId": 511809,
        "mediaType": "movie",
        "backdropPath": "/exnFsbb9c3fDutTsgtJSWcDmZm0.jpg"
    },
    {
        "name": "The Fabelmans",
        "tmdbId": 804095,
        "mediaType": "movie",
        "backdropPath": "/xQyGkQ8ICa4lgifGr3oZjkm3AJ2.jpg"
    },
    {
        "name": "Disclosure Day",
        "tmdbId": 1275779,
        "mediaType": "movie",
        "backdropPath": "/5p6BsJtnPbglYN15MuiUEppPl0f.jpg"
    }
]